agton/ton/__init__.py
agton/ton/utils.py
agton/ton/cell/__init__.py
agton/ton/cell/boc.py
agton/ton/cell/builder.py
agton/ton/cell/cell.py
agton/ton/cell/exceptions.py
agton/ton/cell/slice.py
agton/ton/common/__init__.py
agton/ton/common/bitstring.py
agton/ton/common/bytesparser.py
agton/ton/contracts/__init__.py
agton/ton/contracts/contract.py
agton/ton/crypto/__init__.py
agton/ton/crypto/crc.py
agton/ton/crypto/signing.py
agton/ton/provider/__init__.py
agton/ton/provider/base_api_client.py
agton/ton/provider/provider.py
agton/ton/provider/tonapi.py
agton/ton/provider/toncenter.py
agton/ton/types/__init__.py
agton/ton/types/acc_status_change.py
agton/ton/types/account.py
agton/ton/types/account_state.py
agton/ton/types/account_status.py
agton/ton/types/account_storage.py
agton/ton/types/common_msg_info.py
agton/ton/types/common_msg_info_relaxed.py
agton/ton/types/compute_skip_reason.py
agton/ton/types/continuation.py
agton/ton/types/currency_collection.py
agton/ton/types/hash_update.py
agton/ton/types/hashmap.py
agton/ton/types/message.py
agton/ton/types/message_relaxed.py
agton/ton/types/msg_address.py
agton/ton/types/network.py
agton/ton/types/out_action.py
agton/ton/types/out_list.py
agton/ton/types/shard_account.py
agton/ton/types/state_init.py
agton/ton/types/storage_extra_info.py
agton/ton/types/storage_info.py
agton/ton/types/storage_used.py
agton/ton/types/tlb.py
agton/ton/types/tr_action_phase.py
agton/ton/types/tr_bounce_phase.py
agton/ton/types/tr_compute_phase.py
agton/ton/types/tr_credit_phase.py
agton/ton/types/tr_storage_phase.py
agton/ton/types/transaction.py
agton/ton/types/transaction_descr.py
agton/ton/types/tvm_value.py
agton-0.2.4.dist-info/licenses/LICENSE
agton-0.2.4.dist-info/METADATA
agton-0.2.4.dist-info/WHEEL
agton-0.2.4.dist-info/top_level.txt
agton-0.2.4.dist-info/RECORD
