Metadata-Version: 2.4
Name: agton
Version: 0.2.4
Summary: TON Blockchain SDK
Author-email: Alexey Gosunov <agosunov@gmail.com>
License: MIT
Project-URL: Homepage, https://github.com/gosunov/agton
Requires-Python: >=3.12
License-File: LICENSE
Requires-Dist: PyNaCl>=1.5.0
Requires-Dist: bitarray>=3.0.0
Requires-Dist: requests>=2.32.3
Provides-Extra: wallet
Requires-Dist: agton-wallet>=0.2.4; extra == "wallet"
Provides-Extra: jetton
Requires-Dist: agton-jetton>=0.2.4; extra == "jetton"
Provides-Extra: dedust
Requires-Dist: agton-dedust>=0.2.4; extra == "dedust"
Provides-Extra: all
Requires-Dist: agton-wallet>=0.2.4; extra == "all"
Requires-Dist: agton-jetton>=0.2.4; extra == "all"
Requires-Dist: agton-dedust>=0.2.4; extra == "all"
Dynamic: license-file
